{
    "schema_version": "1.2",
    "packages": [
        {
            "name": "Browser Refresh",
            "description": "This plugin will switch from ST2 to Google Chrome and reload the active tab",
            "author": "Giovanni Collazo (@gcollazo)",
            "homepage": "http://gcollazo.github.com/BrowserRefresh-Sublime",
            "last_modified": "2012-06-28 20:28:00",
            "platforms": {
                "osx": [
                    {
                        "version": "1.0.2",
                        "url": "https://nodeload.github.com/gcollazo/BrowserRefresh-Sublime/zipball/v1.0.2"
                    }
                ]
            }
        }
    ]
}