{
    "schema_version": "1.2",
    "packages": [
        {
            "name": "Browser Refresh",
            "description": "Save the file you are working on and refresh your browser with one keystroke",
            "author": "Giovanni Collazo (@gcollazo)",
            "homepage": "http://gcollazo.github.com/BrowserRefresh-Sublime",
            "readme": "https://raw.github.com/gcollazo/BrowserRefresh-Sublime/master/README.md",
            "last_modified": "2013-08-15 09:40:00",
            "platforms": {
                "osx": [
                    {
                        "version": "1.2.1",
                        "url": "https://github.com/gcollazo/BrowserRefresh-Sublime/archive/1.2.1.tar.gz"
                    }
                ],
                "windows": [
                    {
                        "version": "1.2.1",
                        "url": "https://github.com/gcollazo/BrowserRefresh-Sublime/archive/1.2.1.tar.gz"
                    }
                ]
            },
            "sublime_text": "*"
        }
    ]
}
